LICENSE
rnotify/__init__.py
rnotify/lib/__init__.py
rnotify/lib/file.py
rnotify/lib/folder.py
rnotify/lib/notify.py
rnotify/lib/pid.py
rnotify/lib/utils.py
rnotify/main.py
rnotify-0.1.3.dist-info/entry_points.txt
rnotify-0.1.3.dist-info/LICENSE
rnotify-0.1.3.dist-info/WHEEL
rnotify-0.1.3.dist-info/METADATA
rnotify-0.1.3.dist-info/RECORD
